bytetools/__init__.py
bytetools/py.typed
python_bytetools-0.0.1.dist-info/METADATA
python_bytetools-0.0.1.dist-info/WHEEL
python_bytetools-0.0.1.dist-info/licenses/LICENSE
python_bytetools-0.0.1.dist-info/RECORD
