Metadata-Version: 2.4
Name: python-bytetools
Version: 0.0.1
Summary: Python byte's tools.
License: MIT
License-File: LICENSE
Keywords: byte
Author: ChenyangGao
Author-email: wosiwujm@gmail.com
Requires-Python: >=3.12,<4.0
Classifier: Development Status :: 5 - Production/Stable
Classifier: Intended Audience :: Developers
Classifier: License :: OSI Approved :: MIT License
Classifier: Operating System :: OS Independent
Classifier: Programming Language :: Python
Classifier: Programming Language :: Python :: 3
Classifier: Programming Language :: Python :: 3.12
Classifier: Programming Language :: Python :: 3.13
Classifier: Programming Language :: Python :: 3.14
Classifier: Programming Language :: Python :: 3 :: Only
Classifier: Topic :: Software Development
Classifier: Topic :: Software Development :: Libraries
Classifier: Topic :: Software Development :: Libraries :: Python Modules
Requires-Dist: integer_tool (>=0.0.6)
Project-URL: Homepage, https://github.com/ChenyangGao/python-modules/tree/main/python-bytetools
Project-URL: Repository, https://github.com/ChenyangGao/python-modules/tree/main/python-bytetools
